aemet_forecast/__init__.py
aemet_forecast/_typing.py
aemet_forecast/constants.py
aemet_forecast/main.py
aemet_forecast/utils/__init__.py
aemet_forecast/utils/aemet_http.py
python_aemet_forecast-0.0.1.dist-info/LICENSE
python_aemet_forecast-0.0.1.dist-info/METADATA
python_aemet_forecast-0.0.1.dist-info/WHEEL
python_aemet_forecast-0.0.1.dist-info/top_level.txt
python_aemet_forecast-0.0.1.dist-info/RECORD
